x3d/__init__.py
x3d/x3d.py
x3d.py_brutzman-4.0.64.3.dist-info/LICENSE
x3d.py_brutzman-4.0.64.3.dist-info/METADATA
x3d.py_brutzman-4.0.64.3.dist-info/WHEEL
x3d.py_brutzman-4.0.64.3.dist-info/license.html
x3d.py_brutzman-4.0.64.3.dist-info/license.txt
x3d.py_brutzman-4.0.64.3.dist-info/top_level.txt
x3d.py_brutzman-4.0.64.3.dist-info/RECORD
