Metadata-Version: 2.1
Name: x3d.py-brutzman
Version: 4.0.64.3
Summary: Python package support for Extensible 3D Graphics (X3D) International Standard (IS)
Author-email: Don Brutzman <brutzman@nps.edu>
Project-URL: Homepage, https://www.web3d.org/x3d/stylesheets/python/python.html
Keywords: X3D,3D,graphics,Web3D
Classifier: Programming Language :: Python :: 3
Classifier: License :: OSI Approved :: MIT License
Classifier: Operating System :: OS Independent
Requires-Python: >=3.1
License-File: LICENSE
License-File: license.html
License-File: license.txt
